hatch_autorun/__init__.py
hatch_autorun/hooks.py
hatch_autorun/plugin.py
hatch_autorun-1.1.0.dist-info/METADATA
hatch_autorun-1.1.0.dist-info/WHEEL
hatch_autorun-1.1.0.dist-info/entry_points.txt
hatch_autorun-1.1.0.dist-info/licenses/LICENSE.txt
hatch_autorun-1.1.0.dist-info/RECORD
