Metadata-Version: 2.1
Name: hatch-autorun
Version: 1.1.0
Summary: Hatch build hook plugin to inject code that will automatically run
Project-URL: Funding, https://github.com/sponsors/ofek
Project-URL: History, https://github.com/ofek/hatch-autorun/blob/master/HISTORY.md
Project-URL: Issues, https://github.com/ofek/hatch-autorun/issues
Project-URL: Source, https://github.com/ofek/hatch-autorun
Author-email: Ofek Lev <oss@ofek.dev>
Keywords: autorun,build,hatch,plugin,pth
Classifier: Development Status :: 5 - Production/Stable
Classifier: Framework :: Hatch
Classifier: License :: OSI Approved :: MIT License
Classifier: Programming Language :: Python
Classifier: Programming Language :: Python :: 3.7
Classifier: Programming Language :: Python :: 3.8
Classifier: Programming Language :: Python :: 3.9
Classifier: Programming Language :: Python :: 3.10
Classifier: Programming Language :: Python :: 3.11
Classifier: Programming Language :: Python :: Implementation :: CPython
Classifier: Programming Language :: Python :: Implementation :: PyPy
Classifier: Topic :: Software Development :: Build Tools
Requires-Python: >=3.7
Requires-Dist: hatchling>=1.6.0
